[
  {
    "id": 1,
    "question": "如何创建会议",
    "answer": "点击左侧导航栏中的「新建会议」按钮，选择「即时会议」可立即创建，或选择「预约会议」填写主题、时间和参会人后创建。创建成功后，会议链接会自动复制到剪贴板。",
    "tags": ["meeting_create", "basic", "新建"]
  },
  {
    "id": 2,
    "question": "如何加入别人的会议",
    "answer": "有三种方式加入会议：1) 点击会议邀请链接直接加入；2) 打开 Zoo App，点击「加入会议」并输入会议号；3) 从日程中点击会议卡片直接加入。",
    "tags": ["meeting_join", "basic", "加入"]
  },
  {
    "id": 3,
    "question": "如何共享屏幕",
    "answer": "会议中点击底部工具栏的「共享屏幕」按钮，选择要共享的内容（整个屏幕/应用窗口/白板）。共享时，工具栏会变为绿色提示条，点击「停止共享」可结束。",
    "tags": ["screen_share", "sharing", "共享"]
  },
  {
    "id": 4,
    "question": "如何预约会议",
    "answer": "点击「新建会议」→「预约会议」，填写会议主题、开始时间、时长、参会人（邮箱或手机号），设置好后点击「预约」。系统会自动向参会人发送邮件和日历邀请。",
    "tags": ["schedule_meeting", "booking", "预约"]
  },
  {
    "id": 5,
    "question": "会议中听不到声音怎么办",
    "answer": "请按以下步骤排查：1) 检查本地音量是否开启；2) 点击底部「解除静音」按钮重新开启麦克风；3) 点击「音频设置」检查默认设备是否正确；4) 尝试切换扬声器或耳机；5) 退出重新进入会议。",
    "tags": ["troubleshoot_audio", "audio", "sound", "声音"]
  },
  {
    "id": 6,
    "question": "对方听不到我说话",
    "answer": "请检查：1) 您的麦克风是否被禁用（底部工具栏显示静音图标）；2) 系统是否拦截了麦克风权限；3) 尝试在「音频设置」中切换麦克风设备；4) 重启会议客户端后重试。",
    "tags": ["troubleshoot_audio", "microphone", "麦克风"]
  },
  {
    "id": 7,
    "question": "如何开启视频",
    "answer": "点击底部工具栏的「开始视频」按钮，您的摄像头将开启。如果首次使用，系统会请求摄像头权限，请允许后即可看到自己的画面。再次点击可关闭视频。",
    "tags": ["video", "camera", "视频"]
  },
  {
    "id": 8,
    "question": "视频画面模糊怎么办",
    "answer": "视频模糊可能由以下原因导致：1) 网络带宽不足，请靠近路由器或切换网络；2) 摄像头分辨率设置过低，在「视频设置」中调整分辨率；3) 性能不足，关闭不必要的后台应用。",
    "tags": ["troubleshoot_video", "video", "quality"]
  },
  {
    "id": 9,
    "question": "如何邀请更多人加入会议",
    "answer": "会议中点击底部「参会人」按钮，在弹出的面板中点击「邀请」，可通过搜索联系人、复制会议链接、发送邮件或短信等方式邀请其他人加入。",
    "tags": ["invite", "participants", "邀请"]
  },
  {
    "id": 10,
    "question": "如何录制会议",
    "answer": "主持人点击「更多」→「开始录制」。录制开始后，所有参会人会收到通知。录制完成后，点击「停止录制」，文件会在云端自动处理后发送到主持人邮箱。",
    "tags": ["recording", "record", "录制"]
  },
  {
    "id": 11,
    "question": "录制文件在哪里查看",
    "answer": "录制完成后，文件默认保存在云端。主持人可进入「我的录制」页面查看、下载或分享。也可在会议历史的会议详情页中找到录制链接。",
    "tags": ["recording", "cloud", "查看"]
  },
  {
    "id": 12,
    "question": "如何设置会议密码",
    "answer": "预约会议时，在高级设置中找到「会议密码」选项，开启后设置4-6位数字密码。参会人需输入密码才能加入会议。也可在会议详情中随时修改密码。",
    "tags": ["security", "password", "密码"]
  },
  {
    "id": 13,
    "question": "如何设置等候室",
    "answer": "预约或创建会议时，在高级设置中开启「等候室」功能。开启后，所有参会人需经主持人批准才能进入会议室。可设置允许特定域名的用户直接加入。",
    "tags": ["waiting_room", "security", "等候室"]
  },
  {
    "id": 14,
    "question": "会议中如何切换发言人视图",
    "answer": "点击右上角视图切换按钮，可选择「演讲者视图」（大画面展示当前发言人）和「画廊视图」（所有参会人平铺显示）。快捷键：切换视图可使用快捷键或点击右上角图标。",
    "tags": ["view", "speaker", "视图"]
  },
  {
    "id": 15,
    "question": "如何共享白板",
    "answer": "点击底部「共享」按钮，选择「白板」。白板支持画笔、形状、文字、贴纸等工具。共享后，所有参会人都可以在白板上协作编辑。",
    "tags": ["whiteboard", "share", "白板"]
  },
  {
    "id": 16,
    "question": "会议中如何举手",
    "answer": "点击底部「更多」→「举手」。举手后，主持人会收到通知，可在参会人列表中看到。发言完毕后再点击「放下手」。主持人也可统一放下所有人的手。",
    "tags": ["hand_raise", "interaction", "举手"]
  },
  {
    "id": 17,
    "question": "如何设置虚拟背景",
    "answer": "点击「开始视频」旁的箭头，点击「选择虚拟背景」。可选择系统提供的背景图片、上传自己的图片，或开启虚化背景效果。支持设置会议前预览效果。",
    "tags": ["virtual_background", "video", "背景"]
  },
  {
    "id": 18,
    "question": "会议中断网了怎么办",
    "answer": "如果网络中断：1) 检查本地网络连接；2) Zoo 会自动尝试重连；3) 可点击会议链接重新加入；4) 如果重新加入失败，系统会自动保存聊天记录。",
    "tags": ["troubleshoot_connectivity", "network", "断网"]
  },
  {
    "id": 19,
    "question": "如何更改会议时间",
    "answer": "进入「我的会议」，找到要修改的会议，点击「编辑」。可修改主题、时间、时长、参会人等。修改后系统会自动发送更新通知给所有参会人。",
    "tags": ["edit_meeting", "schedule", "修改"]
  },
  {
    "id": 20,
    "question": "如何删除或取消会议",
    "answer": "进入「我的会议」，找到目标会议，点击「删除」。确认后会议将被取消，系统会自动通知所有已受邀的参会人。正在进行的会议无法删除，只能结束。",
    "tags": ["delete_meeting", "cancel", "删除"]
  },
  {
    "id": 21,
    "question": "会议中没有声音播放",
    "answer": "请检查：1) 确认对方已开启麦克风并正在说话；2) 检查本地扬声器是否静音；3) 在「音频设置」中确认播放设备选择正确；4) 尝试切换播放设备。",
    "tags": ["troubleshoot_audio", "audio", "播放"]
  },
  {
    "id": 22,
    "question": "如何将某人移出会议",
    "answer": "主持人点击「参会人」列表，找到要移除的人，点击其右侧的「移除」按钮。被移除的参会人会收到离开通知，无法再次使用原链接加入（除非主持人重新邀请）。",
    "tags": ["remove_participant", "manage", "移除"]
  },
  {
    "id": 23,
    "question": "会议如何设置同声传译",
    "answer": "在会议高级设置中开启「同声传译」功能，设置语言通道和译员。参会人可在会议中点击「语言」选择要听的语言频道。译员需使用专门的译员客户端。",
    "tags": ["interpretation", "language", "翻译"]
  },
  {
    "id": 24,
    "question": "如何使用会议投票功能",
    "answer": "主持人点击「更多」→「投票」，创建投票主题和选项。发起后，所有参会人可在聊天区看到并投票。投票结束后，主持人可展示结果。",
    "tags": ["poll", "vote", "投票"]
  },
  {
    "id": 25,
    "question": "会议结束后如何获取会议纪要",
    "answer": "如果会议开启了自动纪要功能，会议结束后纪要会自动生成并发送到主持人邮箱。也可在「会议历史」中找到对应会议，点击「查看纪要」手动生成或查看。",
    "tags": ["summary", "notes", "纪要"]
  }
]
